<?xml version="1.0" encoding="UTF-8"?>
<!-- Product Version: Vivado v2019.1 (64-bit)                     -->
<!--                                                              -->
<!-- Copyright 1986-2019 Xilinx, Inc. All Rights Reserved.        -->

<hwsession version="1" minor="2">
  <device name="xc7a35t_0" gui_info="dashboard1=hw_ila_1[xc7a35t_0/hw_ila_1/Settings=ILA_SETTINGS_1;xc7a35t_0/hw_ila_1/Status=ILA_STATUS_1;xc7a35t_0/hw_ila_1/Trigger Setup=ILA_TRIGGER_1;xc7a35t_0/hw_ila_1/Waveform=ILA_WAVE_1;xc7a35t_0/hw_ila_1/Capture Setup=ILA_CAPTURE_1;]"/>
  <ObjectList object_type="hw_device" gui_info="">
    <Object name="xc7a200t_0" gui_info="">
      <Properties Property="FULL_PROBES.FILE" value="$_project_name_.runs/impl_1/FIFO_TOP.ltx"/>
      <Properties Property="PROBES.FILE" value="$_project_name_.runs/impl_1/FIFO_TOP.ltx"/>
      <Properties Property="PROGRAM.HW_BITSTREAM" value="$_project_name_.runs/impl_1/FIFO_TOP.bit"/>
      <Properties Property="SLR.COUNT" value="1"/>
    </Object>
    <Object name="xc7a35t_0" gui_info="">
      <Properties Property="FULL_PROBES.FILE" value="$_project_name_.runs/impl_1/FIFO_TOP.ltx"/>
      <Properties Property="PROBES.FILE" value="$_project_name_.runs/impl_1/FIFO_TOP.ltx"/>
      <Properties Property="PROGRAM.HW_BITSTREAM" value="$_project_name_.runs/impl_1/FIFO_TOP.bit"/>
      <Properties Property="SLR.COUNT" value="1"/>
    </Object>
    <Object name="xc7k325t_0" gui_info="">
      <Properties Property="FULL_PROBES.FILE" value="$_project_name_.runs/impl_1/FIFO_TOP.ltx"/>
      <Properties Property="PROBES.FILE" value="$_project_name_.runs/impl_1/FIFO_TOP.ltx"/>
      <Properties Property="PROGRAM.HW_BITSTREAM" value="$_project_name_.runs/impl_1/FIFO_TOP.bit"/>
      <Properties Property="SLR.COUNT" value="1"/>
    </Object>
    <Object name="xc7z035_1" gui_info="">
      <Properties Property="FULL_PROBES.FILE" value="$_project_name_.runs/impl_1/FIFO_TOP.ltx"/>
      <Properties Property="PROBES.FILE" value="$_project_name_.runs/impl_1/FIFO_TOP.ltx"/>
      <Properties Property="PROGRAM.HW_BITSTREAM" value="$_project_name_.runs/impl_1/FIFO_TOP.bit"/>
      <Properties Property="SLR.COUNT" value="1"/>
    </Object>
    <Object name="xc7z100_1" gui_info="">
      <Properties Property="FULL_PROBES.FILE" value="$_project_name_.runs/impl_1/FIFO_TOP.ltx"/>
      <Properties Property="PROBES.FILE" value="$_project_name_.runs/impl_1/FIFO_TOP.ltx"/>
      <Properties Property="PROGRAM.HW_BITSTREAM" value="$_project_name_.runs/impl_1/FIFO_TOP.bit"/>
      <Properties Property="SLR.COUNT" value="1"/>
    </Object>
  </ObjectList>
  <ObjectList object_type="hw_ila" gui_info="">
    <Object name="" gui_info="">
      <Properties Property="CONTROL.TRIGGER_CONDITION" value="AND"/>
      <Properties Property="CORE_REFRESH_RATE_MS" value="500"/>
    </Object>
    <Object name="u1" gui_info="">
      <Properties Property="CONTROL.TRIGGER_CONDITION" value="AND"/>
      <Properties Property="CORE_REFRESH_RATE_MS" value="500"/>
    </Object>
  </ObjectList>
  <ObjectList object_type="hw_probe" gui_info="">
    <Object name="empty" gui_info="Trigger Setup=0"/>
  </ObjectList>
  <probeset name="hw project" active="false">
    <probe type="ila" busType="bus" source="netlist" spec="ILA_V2_RT">
      <probeOptions Id="DebugProbeParams">
        <Option Id="CAPTURE_COMPARE_VALUE" value="eq16&apos;hXXXX"/>
        <Option Id="COMPARE_VALUE.0" value="eq16&apos;hXXXX"/>
        <Option Id="DISPLAY_AS_ENUM" value="1"/>
        <Option Id="DISPLAY_HINT" value=""/>
        <Option Id="DISPLAY_RADIX" value="UNSIGNED"/>
        <Option Id="DISPLAY_VISIBILITY" value=""/>
        <Option Id="HW_ILA" value="hw_ila_1"/>
        <Option Id="LINK_TO_WAVEFORM" value="1"/>
        <Option Id="MAP" value="probe0[15:0]"/>
        <Option Id="NAME.CUSTOM" value=""/>
        <Option Id="NAME.SELECT" value="Long"/>
        <Option Id="SOURCE" value="netlist"/>
        <Option Id="TRIGGER_COMPARE_VALUE" value="eq16&apos;hXXXX"/>
        <Option Id="WAVEFORM_STYLE" value="Digital"/>
      </probeOptions>
      <nets>
        <net name="din[15]"/>
        <net name="din[14]"/>
        <net name="din[13]"/>
        <net name="din[12]"/>
        <net name="din[11]"/>
        <net name="din[10]"/>
        <net name="din[9]"/>
        <net name="din[8]"/>
        <net name="din[7]"/>
        <net name="din[6]"/>
        <net name="din[5]"/>
        <net name="din[4]"/>
        <net name="din[3]"/>
        <net name="din[2]"/>
        <net name="din[1]"/>
        <net name="din[0]"/>
      </nets>
    </probe>
    <probe type="ila" busType="bus" source="netlist" spec="ILA_V2_RT">
      <probeOptions Id="DebugProbeParams">
        <Option Id="CAPTURE_COMPARE_VALUE" value="eq16&apos;hXXXX"/>
        <Option Id="COMPARE_VALUE.0" value="eq16&apos;hXXXX"/>
        <Option Id="DISPLAY_AS_ENUM" value="1"/>
        <Option Id="DISPLAY_HINT" value=""/>
        <Option Id="DISPLAY_RADIX" value="UNSIGNED"/>
        <Option Id="DISPLAY_VISIBILITY" value=""/>
        <Option Id="HW_ILA" value="hw_ila_1"/>
        <Option Id="LINK_TO_WAVEFORM" value="1"/>
        <Option Id="MAP" value="probe3[15:0]"/>
        <Option Id="NAME.CUSTOM" value=""/>
        <Option Id="NAME.SELECT" value="Long"/>
        <Option Id="SOURCE" value="netlist"/>
        <Option Id="TRIGGER_COMPARE_VALUE" value="eq16&apos;hXXXX"/>
        <Option Id="WAVEFORM_STYLE" value="Digital"/>
      </probeOptions>
      <nets>
        <net name="dout[15]"/>
        <net name="dout[14]"/>
        <net name="dout[13]"/>
        <net name="dout[12]"/>
        <net name="dout[11]"/>
        <net name="dout[10]"/>
        <net name="dout[9]"/>
        <net name="dout[8]"/>
        <net name="dout[7]"/>
        <net name="dout[6]"/>
        <net name="dout[5]"/>
        <net name="dout[4]"/>
        <net name="dout[3]"/>
        <net name="dout[2]"/>
        <net name="dout[1]"/>
        <net name="dout[0]"/>
      </nets>
    </probe>
    <probe type="ila" busType="net" source="netlist" spec="ILA_V2_RT">
      <probeOptions Id="DebugProbeParams">
        <Option Id="CAPTURE_COMPARE_VALUE" value="eq1&apos;bX"/>
        <Option Id="COMPARE_VALUE.0" value="eq1&apos;bF"/>
        <Option Id="DISPLAY_AS_ENUM" value="1"/>
        <Option Id="DISPLAY_HINT" value=""/>
        <Option Id="DISPLAY_RADIX" value="HEX"/>
        <Option Id="DISPLAY_VISIBILITY" value=""/>
        <Option Id="HW_ILA" value="hw_ila_1"/>
        <Option Id="LINK_TO_WAVEFORM" value="1"/>
        <Option Id="MAP" value="probe5[0]"/>
        <Option Id="NAME.CUSTOM" value=""/>
        <Option Id="NAME.SELECT" value="Long"/>
        <Option Id="SOURCE" value="netlist"/>
        <Option Id="TRIGGER_COMPARE_VALUE" value="eq1&apos;bF"/>
        <Option Id="WAVEFORM_STYLE" value="Digital"/>
      </probeOptions>
      <nets>
        <net name="empty"/>
      </nets>
    </probe>
    <probe type="ila" busType="net" source="netlist" spec="ILA_V2_RT">
      <probeOptions Id="DebugProbeParams">
        <Option Id="CAPTURE_COMPARE_VALUE" value="eq1&apos;bX"/>
        <Option Id="COMPARE_VALUE.0" value="eq1&apos;bX"/>
        <Option Id="DISPLAY_AS_ENUM" value="1"/>
        <Option Id="DISPLAY_HINT" value=""/>
        <Option Id="DISPLAY_RADIX" value="HEX"/>
        <Option Id="DISPLAY_VISIBILITY" value=""/>
        <Option Id="HW_ILA" value="hw_ila_1"/>
        <Option Id="LINK_TO_WAVEFORM" value="1"/>
        <Option Id="MAP" value="probe4[0]"/>
        <Option Id="NAME.CUSTOM" value=""/>
        <Option Id="NAME.SELECT" value="Long"/>
        <Option Id="SOURCE" value="netlist"/>
        <Option Id="TRIGGER_COMPARE_VALUE" value="eq1&apos;bX"/>
        <Option Id="WAVEFORM_STYLE" value="Digital"/>
      </probeOptions>
      <nets>
        <net name="full"/>
      </nets>
    </probe>
    <probe type="ila" busType="net" source="netlist" spec="ILA_V2_RT">
      <probeOptions Id="DebugProbeParams">
        <Option Id="CAPTURE_COMPARE_VALUE" value="eq1&apos;bX"/>
        <Option Id="COMPARE_VALUE.0" value="eq1&apos;bX"/>
        <Option Id="DISPLAY_AS_ENUM" value="1"/>
        <Option Id="DISPLAY_HINT" value=""/>
        <Option Id="DISPLAY_RADIX" value="HEX"/>
        <Option Id="DISPLAY_VISIBILITY" value=""/>
        <Option Id="HW_ILA" value="hw_ila_1"/>
        <Option Id="LINK_TO_WAVEFORM" value="1"/>
        <Option Id="MAP" value="probe2[0]"/>
        <Option Id="NAME.CUSTOM" value=""/>
        <Option Id="NAME.SELECT" value="Long"/>
        <Option Id="SOURCE" value="netlist"/>
        <Option Id="TRIGGER_COMPARE_VALUE" value="eq1&apos;bX"/>
        <Option Id="WAVEFORM_STYLE" value="Digital"/>
      </probeOptions>
      <nets>
        <net name="rd_en"/>
      </nets>
    </probe>
    <probe type="ila" busType="net" source="netlist" spec="ILA_V2_RT">
      <probeOptions Id="DebugProbeParams">
        <Option Id="CAPTURE_COMPARE_VALUE" value="eq1&apos;bX"/>
        <Option Id="COMPARE_VALUE.0" value="eq1&apos;bX"/>
        <Option Id="DISPLAY_AS_ENUM" value="1"/>
        <Option Id="DISPLAY_HINT" value=""/>
        <Option Id="DISPLAY_RADIX" value="HEX"/>
        <Option Id="DISPLAY_VISIBILITY" value=""/>
        <Option Id="HW_ILA" value="hw_ila_1"/>
        <Option Id="LINK_TO_WAVEFORM" value="1"/>
        <Option Id="MAP" value="probe1[0]"/>
        <Option Id="NAME.CUSTOM" value=""/>
        <Option Id="NAME.SELECT" value="Long"/>
        <Option Id="SOURCE" value="netlist"/>
        <Option Id="TRIGGER_COMPARE_VALUE" value="eq1&apos;bX"/>
        <Option Id="WAVEFORM_STYLE" value="Digital"/>
      </probeOptions>
      <nets>
        <net name="wr_en"/>
      </nets>
    </probe>
  </probeset>
</hwsession>
